LICENCE.txt
MANIFEST.in
README.md
requirements.txt
setup.cfg
setup.py
RT_EQcorrscan.egg-info/PKG-INFO
RT_EQcorrscan.egg-info/SOURCES.txt
RT_EQcorrscan.egg-info/dependency_links.txt
RT_EQcorrscan.egg-info/entry_points.txt
RT_EQcorrscan.egg-info/requires.txt
RT_EQcorrscan.egg-info/top_level.txt
rt_eqcorrscan/__init__.py
rt_eqcorrscan/rt_match_filter.py
rt_eqcorrscan/config/__init__.py
rt_eqcorrscan/config/config.py
rt_eqcorrscan/console_scripts/__init__.py
rt_eqcorrscan/console_scripts/bench.py
rt_eqcorrscan/console_scripts/build_db.py
rt_eqcorrscan/console_scripts/config.py
rt_eqcorrscan/console_scripts/reactor.py
rt_eqcorrscan/console_scripts/real_time_match.py
rt_eqcorrscan/console_scripts/simulation.py
rt_eqcorrscan/database/__init__.py
rt_eqcorrscan/database/client_emulation.py
rt_eqcorrscan/database/database_manager.py
rt_eqcorrscan/event_trigger/__init__.py
rt_eqcorrscan/event_trigger/catalog_listener.py
rt_eqcorrscan/event_trigger/listener.py
rt_eqcorrscan/event_trigger/triggers.py
rt_eqcorrscan/plotting/__init__.py
rt_eqcorrscan/plotting/plot_buffer.py
rt_eqcorrscan/plotting/plot_event.py
rt_eqcorrscan/reactor/__init__.py
rt_eqcorrscan/reactor/reactor.py
rt_eqcorrscan/reactor/scaling_relations.py
rt_eqcorrscan/reactor/spin_up.py
rt_eqcorrscan/streaming/__init__.py
rt_eqcorrscan/streaming/buffers.py
rt_eqcorrscan/streaming/streaming.py
rt_eqcorrscan/streaming/clients/__init__.py
rt_eqcorrscan/streaming/clients/obsplus.py
rt_eqcorrscan/streaming/clients/obspy.py
rt_eqcorrscan/streaming/clients/seedlink.py